pysimplelog/SimpleLog.py
pysimplelog/__init__.py
pysimplelog/__pkginfo__.py
pysimplelog-4.0.0.dist-info/LICENSE.txt
pysimplelog-4.0.0.dist-info/METADATA
pysimplelog-4.0.0.dist-info/WHEEL
pysimplelog-4.0.0.dist-info/top_level.txt
pysimplelog-4.0.0.dist-info/RECORD
